README.rst
setup.py
dug/__init__.py
dug.egg-info/PKG-INFO
dug.egg-info/SOURCES.txt
dug.egg-info/dependency_links.txt
dug.egg-info/top_level.txt
dug/tests/__init__.py