Metadata-Version: 1.1
Name: dug
Version: 0.1.0
Summary: A python memoisation framework
Home-page: https://github.com/bwhmather/python-dug
Author: Ben Mather
Author-email: bwhmather@bwhmather.com
License: BSD
Platform: UNKNOWN
Classifier: Development Status :: 4 - Beta
Classifier: Intended Audience :: Developers
Classifier: License :: OSI Approved :: BSD License
Classifier: Operating System :: OS Independent
Classifier: Programming Language :: Python :: 3
Classifier: Programming Language :: Python :: 3.4
Classifier: Programming Language :: Python :: 3.5
Classifier: Programming Language :: Python :: 3 :: Only
Classifier: Topic :: Software Development :: Libraries :: Python Modules
